Metadata-Version: 2.4
Name: servc
Version: 1.11.11
Summary: Server implmentation of services for python
Author-email: Yusuf Ali <ali@yusuf.email>
Project-URL: Homepage, https://github.com/serv-c/servc-python
Project-URL: Bug Tracker, https://github.com/serv-c/servc-python/issues
Project-URL: Repository, https://github.com/serv-c/servc-python.git
Project-URL: Documentation, https://docs.servc.io/
Classifier: Programming Language :: Python :: 3
Classifier: License :: OSI Approved :: MIT License
Classifier: Operating System :: OS Independent
Requires-Python: >=3.11
License-File: LICENSE
Dynamic: license-file
